
{
  "assets": {
    "uris": {
      "jre-tar-gz": "http://minio.marathon.l4lb.thisdcos.directory:9000/artifacts/hivemq/server-jre-8u162-linux-x64.tar.gz",
      "libmesos-bundle-tar-gz": "http://minio.marathon.l4lb.thisdcos.directory:9000/artifacts/hivemq/libmesos-bundle-1.11.0.tar.gz",
      "bootstrap-zip": "http://minio.marathon.l4lb.thisdcos.directory:9000/artifacts/hivemq/bootstrap.zip",
      "executor-zip": "https://downloads.mesosphere.com/dcos-commons/artifacts/0.55.2/executor.zip",
      "scheduler-zip": "http://minio.marathon.l4lb.thisdcos.directory:9000/artifacts/hivemq/operator-scheduler.zip",
      "svc": "http://minio.marathon.l4lb.thisdcos.directory:9000/artifacts/hivemq/svc.yml",
      "hivemq-jre": "http://minio.marathon.l4lb.thisdcos.directory:9000/artifacts/hivemq/OpenJDK11U-jre_x64_linux_hotspot_2019-02-03-10-04.tar.gz",
      "hivemq-dcos": "http://minio.marathon.l4lb.thisdcos.directory:9000/artifacts/hivemq/dcos_files.zip",
      "hivemq-rbac": "https://www.hivemq.com/releases/extensions/hivemq-file-rbac-extension-4.0.0.zip",
      "hivemq": "http://hivemq.com/releases/hivemq-4.0.2.zip"
    }
  },
  "images": {
    "icon-small": "http://minio.marathon.l4lb.thisdcos.directory:9000/artifacts/hivemq/icon-hivemq-small.png",
    "icon-medium": "http://minio.marathon.l4lb.thisdcos.directory:9000/artifacts/hivemq/icon-hivemq-medium.png",
    "icon-large": "http://minio.marathon.l4lb.thisdcos.directory:9000/artifacts/hivemq/icon-hivemq-large.png"
  },
  "cli":{
    "binaries":{
      "darwin":{
        "x86-64":{
          "contentHash":[ { "algo":"sha256", "value":"c329d60aa5fea372115c371814a141f6615819db51935bd09a8265c8978115ac" } ],
          "kind":"executable",
          "url":"http://minio.marathon.l4lb.thisdcos.directory:9000/artifacts/hivemq/dcos-service-cli-darwin"
        }
      },
      "linux":{
        "x86-64":{
          "contentHash":[ { "algo":"sha256", "value":"9690330cd5d7017ab7d747e31b28d30f817cf35cb8db700a5ceebaf628d0d299" } ],
          "kind":"executable",
          "url":"https://downloads.mesosphere.com/dcos-commons/artifacts/0.55.2/dcos-service-cli-linux"
        }
      },
      "windows":{
        "x86-64":{
          "contentHash":[ { "algo":"sha256", "value":"75a6d593848f18b6fc5050f7dde18fb91c659b5b62825ba0eca0e8a5286d46bf" } ],
          "kind":"executable",
          "url":"https://downloads.mesosphere.com/dcos-commons/artifacts/0.55.2/dcos-service-cli.exe"
        }
      }
    }
  }
}
